blinkt_sim.py
blinkt_sim-1.0.0.dist-info/DESCRIPTION.rst
blinkt_sim-1.0.0.dist-info/METADATA
blinkt_sim-1.0.0.dist-info/RECORD
blinkt_sim-1.0.0.dist-info/WHEEL
blinkt_sim-1.0.0.dist-info/metadata.json
blinkt_sim-1.0.0.dist-info/top_level.txt
