Metadata-Version: 2.0
Name: blinkt-sim
Version: 1.0.0
Summary: Simulates Pimoroni's Blinkt! using pygame.
Home-page: https://github.com/ottersoftware/blinkt_sim
Author: Simon Wolf
Author-email: simon@ottersoftware.com
License: MIT
Keywords: pimoroni blinkt
Platform: UNKNOWN
Classifier: Development Status :: 5 - Production/Stable
Classifier: Intended Audience :: Developers
Classifier: Topic :: System :: Emulators
Classifier: Topic :: Software Development
Classifier: License :: OSI Approved :: MIT License
Classifier: Programming Language :: Python :: 3 :: Only
Requires-Python: >=3
Requires-Dist: pygame
